agents/github_review/teams.yml
agents/opensource_insight/teams.yml
agents/react_agent/agent.yml
neco_agents/__init__.py
neco_agents/agent/__init__.py
neco_agents/agent/agent.py
neco_agents/agent/teams.py
neco_agents/backend/__init__.py
neco_agents/backend/backend_factory.py
neco_agents/backend/base_backend.py
neco_agents/backend/local_backend.py
neco_agents/backend/notion_backend.py
neco_agents/cli/__init__.py
neco_agents/cli/bootstrap.py
neco_agents/tools/__init__.py
neco_agents/tools/execute_tool.py
neco_agents/tools/github_tool.py
neco_agents/tools/scraper.py
neco_agents/tools/wecom_bot.py
neco_agents-0.2.0.dist-info/METADATA
neco_agents-0.2.0.dist-info/WHEEL
neco_agents-0.2.0.dist-info/entry_points.txt
neco_agents-0.2.0.dist-info/top_level.txt
neco_agents-0.2.0.dist-info/RECORD
