Metadata-Version: 2.4
Name: neco_agents
Version: 0.2.0
Requires-Python: >=3.12
Requires-Dist: fire>=0.7.1
Requires-Dist: loguru>=0.7.3
Requires-Dist: python-dotenv>=1.2.1
Requires-Dist: tqdm>=4.67.1
Requires-Dist: requests>=2.32.5
Requires-Dist: agno[tools]>=2.2.7
Requires-Dist: notion-client>=2.7.0
Requires-Dist: fastapi[standard]>=0.115.14
